giteapython/__init__.py
giteapython/api_client.py
giteapython/configuration.py
giteapython/rest.py
giteapython/api/__init__.py
giteapython/api/admin_api.py
giteapython/api/issue_api.py
giteapython/api/miscellaneous_api.py
giteapython/api/notification_api.py
giteapython/api/organization_api.py
giteapython/api/repository_api.py
giteapython/api/user_api.py
giteapython/models/__init__.py
giteapython/models/access_token.py
giteapython/models/add_collaborator_option.py
giteapython/models/add_time_option.py
giteapython/models/annotated_tag.py
giteapython/models/annotated_tag_object.py
giteapython/models/api_error.py
giteapython/models/attachment.py
giteapython/models/branch.py
giteapython/models/branch_protection.py
giteapython/models/comment.py
giteapython/models/commit.py
giteapython/models/commit_date_options.py
giteapython/models/commit_meta.py
giteapython/models/commit_user.py
giteapython/models/contents_response.py
giteapython/models/create_branch_protection_option.py
giteapython/models/create_email_option.py
giteapython/models/create_file_options.py
giteapython/models/create_fork_option.py
giteapython/models/create_gpg_key_option.py
giteapython/models/create_hook_option.py
giteapython/models/create_hook_option_config.py
giteapython/models/create_issue_comment_option.py
giteapython/models/create_issue_option.py
giteapython/models/create_key_option.py
giteapython/models/create_label_option.py
giteapython/models/create_milestone_option.py
giteapython/models/create_o_auth2_application_options.py
giteapython/models/create_org_option.py
giteapython/models/create_pull_request_option.py
giteapython/models/create_pull_review_comment.py
giteapython/models/create_pull_review_options.py
giteapython/models/create_release_option.py
giteapython/models/create_repo_option.py
giteapython/models/create_status_option.py
giteapython/models/create_team_option.py
giteapython/models/create_user_option.py
giteapython/models/delete_email_option.py
giteapython/models/delete_file_options.py
giteapython-1.12.2.dist-info/LICENSE
giteapython-1.12.2.dist-info/METADATA
giteapython-1.12.2.dist-info/WHEEL
giteapython-1.12.2.dist-info/top_level.txt
giteapython-1.12.2.dist-info/RECORD
