Metadata-Version: 2.1
Name: giteapython
Version: 1.12.2
Summary: Gitea API.
Home-page: https://git.cynarski.pl/python/giteapython
Author-email: paramah@gmail.com
License: UNKNOWN
Keywords: Swagger,Gitea API.,gitea,git
Platform: UNKNOWN
Classifier: Programming Language :: Python :: 3
Classifier: License :: OSI Approved :: MIT License
Classifier: Operating System :: OS Independent
Requires-Python: >=3.6
Requires-Dist: certifi (>=2017.4.17)
Requires-Dist: python-dateutil (>=2.1)
Requires-Dist: six (>=1.10)
Requires-Dist: urllib3 (>=1.23)
